magic_key/___init___.py
magic_key/magics.py
magic_key/manager.py
magic_key/memory.py
magic_key/prompt.txt
magic_key-0.3.dist-info/LICENSE
magic_key-0.3.dist-info/METADATA
magic_key-0.3.dist-info/WHEEL
magic_key-0.3.dist-info/top_level.txt
magic_key-0.3.dist-info/RECORD
