Metadata-Version: 2.1
Name: magic-key
Version: 0.3
Summary: This module provides iPython integration and magics that allow exact, inexact and intellegent code execution.
Home-page: https://gitlab.com/mcaledonensis/magic-key
Author: Merlinus Caledonensis
Author-email: merlin@roundtable.game
License: Apache 2.0
License-File: LICENSE
